[
  {
    "videoId": "lh8dNmneVyY",
    "tags": ["北アメリカ", "カナダ", "バンクーバー", "ダウンタウン"]
  },
  {
    "videoId": "3EaCj-seAHM",
    "tags": ["北アメリカ", "アメリカ", "シアトル", "ダウンタウン"]
  },
  {
    "videoId": "eJeF7hDB0UA",
    "tags": ["ヨーロッパ", "イタリア", "ローマ", "コロッセウム", "世界遺産"]
  },
  {
    "videoId": "unSFkZQiqDs",
    "tags": ["ヨーロッパ", "ロシア", "サンクトペテルブルク", "街", "公園"]
  },
  {
    "videoId": "NYUWOdMkay0",
    "tags": ["アジア", "イスラエル", "ユートピアオーキッドパーク", "植物園"]
  },
  {
    "videoId": "EaQr917lRgI",
    "tags": ["アフリカ", "エジプト", "ギザ", "ピラミッド", "世界遺産"]
  },
  {
    "videoId": "YVYDz_coSfY",
    "tags": ["アフリカ", "エジプト", "カイロ", "首都", "旧市街", "世界遺産"]
  },
  {
    "videoId": "s0HGEcMUVtg",
    "tags": ["オセアニア", "オーストラリア", "メルボルン", "街"]
  },
  {
    "videoId": "LoUxi2HdbYA",
    "tags": ["南アメリカ", "アルゼンチン", "ブエノスアイレス", "首都", "街"]
  },
  {
    "videoId": "Jf3MrsUej98",
    "tags": ["北アメリカ", "アメリカ", "ハワイ", "ワイキキ"]
  },
  {
    "videoId": "OsnRSr7LxII",
    "tags": ["アフリカ", "モロッコ", "マラケシュ", "街"]
  },
  {
    "videoId": "CjLTzAYD3GA",
    "tags": ["ヨーロッパ", "ラトビア", "リガ", "首都", "世界遺産", "旧市街", "公園"]
  },
  {
    "videoId": "co6L9jw_Wno",
    "tags": ["アジア", "イスラエル", "テルアビブ", "地中海沿岸", "街", "公園"]
  },
  {
    "videoId": "_HOfihkdTsc",
    "tags": ["アジア", "インド", "コルカタ", "街", "市場"]
  },
  {
    "videoId": "C796Mh7kMM8",
    "tags": ["アジア", "トルコ", "イスタンブール", "旧市街"]
  },
  {
    "videoId": "kJgQ1HHf7sk",
    "tags": ["ヨーロッパ", "ドイツ", "バイエルン", "ローテンブルク", "旧市街"]
  },
  {
    "videoId": "dHbLCfbdUVo",
    "tags": ["ヨーロッパ", "ハンガリー", "ブダペスト", "首都", "世界遺産", "公園"]
  },
  {
    "videoId": "7WQZNe35LRY",
    "tags": ["アジア", "タイ", "プーケット", "パトンビーチ", "バングラ通り", "海"]
  },
  {
    "videoId": "hCFT2HkBRnI",
    "tags": ["ヨーロッパ", "マルタ", "バレッタ", "首都", "世界遺産", "地中海"]
  },
  {
    "videoId": "hydz8tf7d7s",
    "tags": ["アジア", "マレーシア", "クアラルンプール", "首都"]
  },
  {
    "videoId": "aUJl46bEWYo",
    "tags": ["アジア", "シンガポール", "チャイナタウン", "マリーナベイ・サンズ", "中華街"]
  },
  {
    "videoId": "OHMk5ah8xfU",
    "tags": ["ヨーロッパ", "スウェーデン", "ストックホルム", "首都", "旧市街"]
  },
  {
    "videoId": "VQ8O4pkRiCE",
    "tags": ["ヨーロッパ", "ブルガリア", "プロヴディフ", "遺跡", "旧市街", "公園"]
  },
  {
    "videoId": "_KNINBNRneo",
    "tags": ["ヨーロッパ", "ボスニア・ヘルツェゴビナ", "モスタル", "旧市街", "川", "公園"]
  },
  {
    "videoId": "Y5TNhAMEm5g",
    "tags": ["ヨーロッパ", "フランス", "パリ", "首都", "世界遺産", "旧市街", "公園"]
  },
  {
    "videoId": "-ZXjFeBd9Us",
    "tags": ["ヨーロッパ", "スペイン", "バルセロナ", "世界遺産", "旧市街", "公園"]
  },
  {
    "videoId": "-IpXdtWfneI",
    "tags": ["北アメリカ", "アメリカ", "ニューヨーク", "マンハッタン", "街", "公園"]
  },
  {
    "videoId": "SCwZ_fMtp_E",
    "tags": ["北アメリカ", "アメリカ", "カリフォルニア", "ディズニーランド", "遊園地"]
  },
  {
    "videoId": "poiKJGuLDNo",
    "tags": ["北アメリカ", "カナダ", "モントリオール", "世界遺産", "旧市街", "公園"]
  },
  {
    "videoId": "3laHW-dc_ac",
    "tags": ["ヨーロッパ", "オランダ", "アムステルダム", "首都", "世界遺産", "旧市街", "運河"]
  },
  {
    "videoId": "I0uHWW7EnOM",
    "tags": ["オセアニア", "フィジー", "ナディ", "島", "海"]
  },
  {
    "videoId": "y7zhnCmGvi8",
    "tags": ["オセアニア", "ニュージーランド", "オークランド", "街", "公園"]
  },
  {
    "videoId": "HhVMMfe6tuo",
    "tags": ["ヨーロッパ", "オーストリア", "ザルツブルク", "世界遺産", "歴史地区"]
  },
  {
    "videoId": "q8L2edie1v0",
    "tags": ["ヨーロッパ", "ポルトガル", "ポルト", "世界遺産", "旧市街", "海岸都市"]
  },
  {
    "videoId": "tNJTWOUH8JE",
    "tags": ["ヨーロッパ", "チェコ", "プラハ", "首都", "世界遺産", "旧市街"]
  },
  {
    "videoId": "AJNh9zZm2wI",
    "tags": ["ヨーロッパ", "モンテネグロ", "コトル", "世界遺産", "旧市街"]
  },
  {
    "videoId": "buBU7NrfyGM",
    "tags": ["ヨーロッパ", "チェコ", "チェスキークルムロフ", "世界遺産", "旧市街"]
  },
  {
    "videoId": "kmmAQ7ZCf4E",
    "tags": ["ヨーロッパ", "エストニア", "タリン", "首都", "世界遺産", "バルト海"]
  },
  {
    "videoId": "wRZf8-B6GGk",
    "tags": ["ヨーロッパ", "ポーランド", "クラクフ", "世界遺産", "旧市街", "公園"]
  },
  {
    "videoId": "zZmTLjBY7a8",
    "tags": ["南アメリカ", "エクアドル", "キト", "首都", "世界遺産"]
  },
  {
    "videoId": "seOSZlVPdgM",
    "tags": ["ヨーロッパ", "イタリア", "ローマ", "世界遺産", "旧市街", "広場"]
  }
]